README.md
setup.py
n3th0us3/__init__.py
n3th0us3/colorizers.py
n3th0us3/domains.py
n3th0us3.egg-info/PKG-INFO
n3th0us3.egg-info/SOURCES.txt
n3th0us3.egg-info/dependency_links.txt
n3th0us3.egg-info/top_level.txt