Metadata-Version: 2.1
Name: n3th0us3
Version: 1.1.2
Summary: Unofficial python package for domains.nethouse.ru service.
Home-page: UNKNOWN
Author: Anzhela
Author-email: dev.anzhela@gmail.com
License: UNKNOWN
Platform: UNKNOWN
Classifier: Programming Language :: Python :: 3
Classifier: Operating System :: OS Independent
Requires-Python: >=3.4
